cowptain/__init__.py
cowptain/app.py
cowptain/const.py
cowptain/errors.py
cowptain/headers.py
cowptain/path.py
cowptain/re.py
cowptain/routing.py
cowptain/utils.py
cowptain/view.py
cowptain-0.0.5.dist-info/LICENSE
cowptain-0.0.5.dist-info/METADATA
cowptain-0.0.5.dist-info/WHEEL
cowptain-0.0.5.dist-info/top_level.txt
cowptain-0.0.5.dist-info/RECORD
