Metadata-Version: 2.1
Name: cowptain
Version: 0.0.5
Summary: Python web nanoframework
Author: zuczekgnojak
Project-URL: Homepage, https://github.com/zuczekgnojak/cowptain
Classifier: Programming Language :: Python :: 3
Classifier: License :: OSI Approved :: MIT License
Classifier: Operating System :: OS Independent
Requires-Python: >=3.10
License-File: LICENSE
